__init__.py
effectsize.py
functions.py
effectsize-0.0.3.dist-info/METADATA
effectsize-0.0.3.dist-info/WHEEL
effectsize-0.0.3.dist-info/top_level.txt
effectsize-0.0.3.dist-info/RECORD
