Metadata-Version: 2.1
Name: effectsize
Version: 0.0.3
Summary: Computing effect sizes in Python
Home-page: https://github.com/nbashir97/effectsize
Author: Nasir Bashir
Author-email: Nasir Bashir <nbashir562@gmail.com>
Project-URL: Homepage, https://github.com/nbashir97/effectsize
Platform: any
Classifier: Programming Language :: Python :: 3
Classifier: Operating System :: OS Independent
Classifier: License :: OSI Approved :: MIT License
Classifier: Intended Audience :: Science/Research
Requires-Python: >=3.7
License-File: LICENSE.md
Requires-Dist: pandas
Requires-Dist: numpy
Requires-Dist: scipy
Requires-Dist: statsmodels
